streamlit_azure_kit/__init__.py
streamlit_azure_kit/version.py
streamlit_azure_kit/auth/__init__.py
streamlit_azure_kit/auth/auth_handler.py
streamlit_azure_kit/config/__init__.py
streamlit_azure_kit/config/blob_loader.py
streamlit_azure_kit/config/config_loader.py
streamlit_azure_kit/database/__init__.py
streamlit_azure_kit/database/connections.py
streamlit_azure_kit/database/storage.py
streamlit_azure_kit/datetime/__init__.py
streamlit_azure_kit/datetime/datetime_utils.py
streamlit_azure_kit-0.3.4.dist-info/LICENSE
streamlit_azure_kit-0.3.4.dist-info/METADATA
streamlit_azure_kit-0.3.4.dist-info/WHEEL
streamlit_azure_kit-0.3.4.dist-info/top_level.txt
streamlit_azure_kit-0.3.4.dist-info/RECORD
