Metadata-Version: 2.1
Name: streamlit-azure-kit
Version: 0.3.4
Summary: Configuration-driven database and storage utilities for Azure
Home-page: https://github.com/streamlit-azure-kit/streamlit-azure-kit
Author: Streamlit Azure Kit
Author-email: noreply@example.com
License: UNKNOWN
Platform: UNKNOWN
Classifier: Development Status :: 4 - Beta
Classifier: Intended Audience :: Developers
Classifier: License :: OSI Approved :: MIT License
Classifier: Operating System :: OS Independent
Classifier: Programming Language :: Python :: 3
Classifier: Programming Language :: Python :: 3.9
Classifier: Programming Language :: Python :: 3.10
Classifier: Programming Language :: Python :: 3.11
Classifier: Programming Language :: Python :: 3.12
Classifier: Topic :: Database
Classifier: Topic :: Software Development :: Libraries :: Python Modules
Requires-Python: >=3.9
License-File: LICENSE
Requires-Dist: sqlalchemy>=2.0.0
Requires-Dist: pandas>=2.0.0
Requires-Dist: azure-identity>=1.14.0
Requires-Dist: azure-storage-blob>=12.0.0
Requires-Dist: pyodbc>=4.0.0
Requires-Dist: python-dotenv>=1.0.0
